pintpandas/__init__.py
pintpandas/pint_array.py
pintpandas/test_pandas_interface.py
Pint_Pandas_Fork-0.1.dev0.dist-info/LICENSE
Pint_Pandas_Fork-0.1.dev0.dist-info/METADATA
Pint_Pandas_Fork-0.1.dev0.dist-info/WHEEL
Pint_Pandas_Fork-0.1.dev0.dist-info/top_level.txt
Pint_Pandas_Fork-0.1.dev0.dist-info/RECORD
